[{"pk":33,"model":"accounts.City","fields":{"name":"آسمان آباد"}},{"pk":34,"model":"accounts.City","fields":{"name":"آرادان"}},{"pk":35,"model":"accounts.City","fields":{"name":"آغاجاری"}},{"pk":36,"model":"accounts.City","fields":{"name":"آبادان"}},{"pk":37,"model":"accounts.City","fields":{"name":"آران و بیدگل"}},{"pk":38,"model":"accounts.City","fields":{"name":"آمل"}},{"pk":39,"model":"accounts.City","fields":{"name":"آباده"}},{"pk":40,"model":"accounts.City","fields":{"name":"آرمرده"}},{"pk":41,"model":"accounts.City","fields":{"name":"آوج"}},{"pk":42,"model":"accounts.City","fields":{"name":"آباده طشک"}},{"pk":43,"model":"accounts.City","fields":{"name":"آریاشهر"}},{"pk":44,"model":"accounts.City","fields":{"name":"آرین شهر"}},{"pk":45,"model":"accounts.City","fields":{"name":"آبسرد"}},{"pk":46,"model":"accounts.City","fields":{"name":"آزادشهر"}},{"pk":47,"model":"accounts.City","fields":{"name":"آبدانان"}},{"pk":48,"model":"accounts.City","fields":{"name":"آبگرم"}},{"pk":49,"model":"accounts.City","fields":{"name":"آستارا"}},{"pk":50,"model":"accounts.City","fields":{"name":"آیسک"}},{"pk":51,"model":"accounts.City","fields":{"name":"آبیک"}},{"pk":52,"model":"accounts.City","fields":{"name":"آستانه اشرفیه"}},{"pk":53,"model":"accounts.City","fields":{"name":"آذرشهر"}},{"pk":54,"model":"accounts.City","fields":{"name":"آشتیان"}},{"pk":55,"model":"accounts.City","fields":{"name":"آشخانه"}},{"pk":56,"model":"accounts.City","fields":{"name":"ابرکوه"}},{"pk":57,"model":"accounts.City","fields":{"name":"اسفدن"}},{"pk":58,"model":"accounts.City","fields":{"name":"امیدیه (شهر) (صفحه وجود ندارد)"}},{"pk":59,"model":"accounts.City","fields":{"name":"ابهر"}},{"pk":60,"model":"accounts.City","fields":{"name":"اسفراین"}},{"pk":61,"model":"accounts.City","fields":{"name":"اندیشه (شهر)"}},{"pk":62,"model":"accounts.City","fields":{"name":"ابوزیدآباد"}},{"pk":63,"model":"accounts.City","fields":{"name":"اسفرورین"}},{"pk":64,"model":"accounts.City","fields":{"name":"اندیمشک"}},{"pk":65,"model":"accounts.City","fields":{"name":"اراک"}},{"pk":66,"model":"accounts.City","fields":{"name":"اسکو"}},{"pk":67,"model":"accounts.City","fields":{"name":"اوز"}},{"pk":68,"model":"accounts.City","fields":{"name":"ارداق"}},{"pk":69,"model":"accounts.City","fields":{"name":"اسلام‌آباد غرب"}},{"pk":70,"model":"accounts.City","fields":{"name":"اهر"}},{"pk":71,"model":"accounts.City","fields":{"name":"اردبیل"}},{"pk":72,"model":"accounts.City","fields":{"name":"اسلام‌شهر"}},{"pk":73,"model":"accounts.City","fields":{"name":"اهل (شهر)"}},{"pk":74,"model":"accounts.City","fields":{"name":"املش"}},{"pk":75,"model":"accounts.City","fields":{"name":"اسلامیه"}},{"pk":76,"model":"accounts.City","fields":{"name":"اهواز"}},{"pk":77,"model":"accounts.City","fields":{"name":"اردستان"}},{"pk":78,"model":"accounts.City","fields":{"name":"اشنویه"}},{"pk":79,"model":"accounts.City","fields":{"name":"اشتهارد"}},{"pk":80,"model":"accounts.City","fields":{"name":"اردکان"}},{"pk":81,"model":"accounts.City","fields":{"name":"اشکنان"}},{"pk":82,"model":"accounts.City","fields":{"name":"ایزدخواست"}},{"pk":83,"model":"accounts.City","fields":{"name":"ارسنجان"}},{"pk":84,"model":"accounts.City","fields":{"name":"اصفهان"}},{"pk":85,"model":"accounts.City","fields":{"name":"ایذه"}},{"pk":86,"model":"accounts.City","fields":{"name":"ارومیه"}},{"pk":87,"model":"accounts.City","fields":{"name":"اقبالیه"}},{"pk":88,"model":"accounts.City","fields":{"name":"ایرانشهر"}},{"pk":89,"model":"accounts.City","fields":{"name":"ازنا"}},{"pk":90,"model":"accounts.City","fields":{"name":"اقلید"}},{"pk":91,"model":"accounts.City","fields":{"name":"ایلام"}},{"pk":92,"model":"accounts.City","fields":{"name":"اژیه"}},{"pk":93,"model":"accounts.City","fields":{"name":"الشتر"}},{"pk":94,"model":"accounts.City","fields":{"name":"ایوانکی"}},{"pk":95,"model":"accounts.City","fields":{"name":"استهبان"}},{"pk":96,"model":"accounts.City","fields":{"name":"الوند (شهر)"}},{"pk":97,"model":"accounts.City","fields":{"name":"ایوان غرب"}},{"pk":98,"model":"accounts.City","fields":{"name":"اسدآباد"}},{"pk":99,"model":"accounts.City","fields":{"name":"الیگودرز"}},{"pk":100,"model":"accounts.City","fields":{"name":"اسدیه"}},{"pk":101,"model":"accounts.City","fields":{"name":"بلبان آباد"}},{"pk":102,"model":"accounts.City","fields":{"name":"بندر امام خمینی"}},{"pk":103,"model":"accounts.City","fields":{"name":"بهارستان (شهر)"}},{"pk":104,"model":"accounts.City","fields":{"name":"بافق"}},{"pk":105,"model":"accounts.City","fields":{"name":"بندرانزلی"}},{"pk":106,"model":"accounts.City","fields":{"name":"بهبهان"}},{"pk":107,"model":"accounts.City","fields":{"name":"بالاده"}},{"pk":108,"model":"accounts.City","fields":{"name":"بندرترکمن"}},{"pk":109,"model":"accounts.City","fields":{"name":"بهشهر"}},{"pk":110,"model":"accounts.City","fields":{"name":"بانه"}},{"pk":111,"model":"accounts.City","fields":{"name":"بندرعباس"}},{"pk":112,"model":"accounts.City","fields":{"name":"بهمن (شهر)"}},{"pk":113,"model":"accounts.City","fields":{"name":"بجنورد"}},{"pk":114,"model":"accounts.City","fields":{"name":"بندرلنگه"}},{"pk":115,"model":"accounts.City","fields":{"name":"بیارجمند"}},{"pk":116,"model":"accounts.City","fields":{"name":"بازنه"}},{"pk":117,"model":"accounts.City","fields":{"name":"شهر مهاجران (صفحه وجود ندارد)"}},{"pk":118,"model":"accounts.City","fields":{"name":"شازند"}},{"pk":119,"model":"accounts.City","fields":{"name":"بخشایش"}},{"pk":120,"model":"accounts.City","fields":{"name":"برازجان"}},{"pk":121,"model":"accounts.City","fields":{"name":"بندرگز"}},{"pk":122,"model":"accounts.City","fields":{"name":"بیجار"}},{"pk":123,"model":"accounts.City","fields":{"name":"بردسکن"}},{"pk":124,"model":"accounts.City","fields":{"name":"بندر خمیر"}},{"pk":125,"model":"accounts.City","fields":{"name":"بیدخت"}},{"pk":126,"model":"accounts.City","fields":{"name":"بردسیر"}},{"pk":127,"model":"accounts.City","fields":{"name":"بویین میاندشت"}},{"pk":128,"model":"accounts.City","fields":{"name":"بیدستان"}},{"pk":129,"model":"accounts.City","fields":{"name":"بروجرد"}},{"pk":130,"model":"accounts.City","fields":{"name":"بوئین زهرا"}},{"pk":131,"model":"accounts.City","fields":{"name":"بیرجند"}},{"pk":132,"model":"accounts.City","fields":{"name":"بروجن"}},{"pk":133,"model":"accounts.City","fields":{"name":"بوئین سفلی"}},{"pk":134,"model":"accounts.City","fields":{"name":"بیرم"}},{"pk":135,"model":"accounts.City","fields":{"name":"بسطام"}},{"pk":136,"model":"accounts.City","fields":{"name":"بوانات"}},{"pk":137,"model":"accounts.City","fields":{"name":"بیضا"}},{"pk":138,"model":"accounts.City","fields":{"name":"بیله سوار"}},{"pk":139,"model":"accounts.City","fields":{"name":"پارس‌آباد"}},{"pk":140,"model":"accounts.City","fields":{"name":"پردیس (تهران)"}},{"pk":141,"model":"accounts.City","fields":{"name":"پیرانشهر"}},{"pk":142,"model":"accounts.City","fields":{"name":"پاکدشت"}},{"pk":143,"model":"accounts.City","fields":{"name":"پلدشت"}},{"pk":144,"model":"accounts.City","fields":{"name":"پیشوا"}},{"pk":145,"model":"accounts.City","fields":{"name":"پاوه"}},{"pk":146,"model":"accounts.City","fields":{"name":"فولادشهر"}},{"pk":147,"model":"accounts.City","fields":{"name":"تازه‌شهر"}},{"pk":148,"model":"accounts.City","fields":{"name":"تربت حیدریه"}},{"pk":149,"model":"accounts.City","fields":{"name":"تودشک"}},{"pk":150,"model":"accounts.City","fields":{"name":"تاکستان"}},{"pk":151,"model":"accounts.City","fields":{"name":"تجریش"}},{"pk":152,"model":"accounts.City","fields":{"name":"تویسرکان"}},{"pk":153,"model":"accounts.City","fields":{"name":"تالش"}},{"pk":154,"model":"accounts.City","fields":{"name":"هشتپر"}},{"pk":155,"model":"accounts.City","fields":{"name":"تفت"}},{"pk":156,"model":"accounts.City","fields":{"name":"تهران"}},{"pk":157,"model":"accounts.City","fields":{"name":"تایباد"}},{"pk":158,"model":"accounts.City","fields":{"name":"تفرش"}},{"pk":159,"model":"accounts.City","fields":{"name":"تیران"}},{"pk":160,"model":"accounts.City","fields":{"name":"تبریز"}},{"pk":161,"model":"accounts.City","fields":{"name":"تکاب"}},{"pk":162,"model":"accounts.City","fields":{"name":"تربت جام"}},{"pk":163,"model":"accounts.City","fields":{"name":"تنکابن"}},{"pk":164,"model":"accounts.City","fields":{"name":"جاجرم"}},{"pk":165,"model":"accounts.City","fields":{"name":"جنت‌شهر"}},{"pk":166,"model":"accounts.City","fields":{"name":"جویم"}},{"pk":167,"model":"accounts.City","fields":{"name":"جاجرود"}},{"pk":168,"model":"accounts.City","fields":{"name":"جناح (شهر)"}},{"pk":169,"model":"accounts.City","fields":{"name":"جهرم"}},{"pk":170,"model":"accounts.City","fields":{"name":"جعفریه (شهر)"}},{"pk":171,"model":"accounts.City","fields":{"name":"جوادآباد"}},{"pk":172,"model":"accounts.City","fields":{"name":"جیرنده"}},{"pk":173,"model":"accounts.City","fields":{"name":"جلفا"}},{"pk":174,"model":"accounts.City","fields":{"name":"جوانرود"}},{"pk":175,"model":"accounts.City","fields":{"name":"جیرفت"}},{"pk":176,"model":"accounts.City","fields":{"name":"جم"}},{"pk":177,"model":"accounts.City","fields":{"name":"جویبار"}},{"pk":178,"model":"accounts.City","fields":{"name":"جندق"}},{"pk":179,"model":"accounts.City","fields":{"name":"جوکندان"}},{"pk":180,"model":"accounts.City","fields":{"name":"جق کرمک (صفحه وجود ندارد)"}},{"pk":181,"model":"accounts.City","fields":{"name":"جاسک"}},{"pk":182,"model":"accounts.City","fields":{"name":"چابکسر"}},{"pk":183,"model":"accounts.City","fields":{"name":"چمران (شهر)"}},{"pk":184,"model":"accounts.City","fields":{"name":"چناره"}},{"pk":185,"model":"accounts.City","fields":{"name":"چابهار"}},{"pk":186,"model":"accounts.City","fields":{"name":"چمستان"}},{"pk":187,"model":"accounts.City","fields":{"name":"چهاردانگه"}},{"pk":188,"model":"accounts.City","fields":{"name":"چادگان"}},{"pk":189,"model":"accounts.City","fields":{"name":"چناران"}},{"pk":190,"model":"accounts.City","fields":{"name":"چم گردان"}},{"pk":191,"model":"accounts.City","fields":{"name":"چالوس"}},{"pk":192,"model":"accounts.City","fields":{"name":"چم کبود (صفحه وجود ندارد)"}},{"pk":193,"model":"accounts.City","fields":{"name":"حاجی‌آباد (خراسان جنوبی)"}},{"pk":194,"model":"accounts.City","fields":{"name":"حسن‌آباد (شهر) (صفحه وجود ندارد)"}},{"pk":195,"model":"accounts.City","fields":{"name":"حصارک"}},{"pk":196,"model":"accounts.City","fields":{"name":"حاجی‌آباد (استان اصفهان) (صفحه وجود ندارد)"}},{"pk":197,"model":"accounts.City","fields":{"name":"حسن‌آباد (استان اصفهان) (صفحه وجود ندارد)"}},{"pk":198,"model":"accounts.City","fields":{"name":"حنا (شهر)"}},{"pk":199,"model":"accounts.City","fields":{"name":"حبیب‌آباد (استان اصفهان) (صفحه وجود ندارد)"}},{"pk":200,"model":"accounts.City","fields":{"name":"حسینیه (استان خوزستان) (صفحه وجود ندارد)"}},{"pk":201,"model":"accounts.City","fields":{"name":"خرمدره"}},{"pk":202,"model":"accounts.City","fields":{"name":"خشت (شهر)"}},{"pk":203,"model":"accounts.City","fields":{"name":"خور (اصفهان)"}},{"pk":204,"model":"accounts.City","fields":{"name":"خارک"}},{"pk":205,"model":"accounts.City","fields":{"name":"خضری دشت بیاض"}},{"pk":206,"model":"accounts.City","fields":{"name":"خور (لار)"}},{"pk":207,"model":"accounts.City","fields":{"name":"خاش"}},{"pk":208,"model":"accounts.City","fields":{"name":"خلخال"}},{"pk":209,"model":"accounts.City","fields":{"name":"خوراسگان"}},{"pk":210,"model":"accounts.City","fields":{"name":"خامنه"}},{"pk":211,"model":"accounts.City","fields":{"name":"خلیل‌آباد"}},{"pk":212,"model":"accounts.City","fields":{"name":"خورزوق"}},{"pk":213,"model":"accounts.City","fields":{"name":"خاوران (شهر)"}},{"pk":214,"model":"accounts.City","fields":{"name":"خمام"}},{"pk":215,"model":"accounts.City","fields":{"name":"خور و بیابانک"}},{"pk":216,"model":"accounts.City","fields":{"name":"خدابنده"}},{"pk":217,"model":"accounts.City","fields":{"name":"خمین"}},{"pk":218,"model":"accounts.City","fields":{"name":"خورموج"}},{"pk":219,"model":"accounts.City","fields":{"name":"خرامه"}},{"pk":220,"model":"accounts.City","fields":{"name":"خمینی‌شهر"}},{"pk":221,"model":"accounts.City","fields":{"name":"خوسف"}},{"pk":222,"model":"accounts.City","fields":{"name":"خرم‌آباد"}},{"pk":223,"model":"accounts.City","fields":{"name":"خنج"}},{"pk":224,"model":"accounts.City","fields":{"name":"خواف"}},{"pk":225,"model":"accounts.City","fields":{"name":"خرم‌دشت (صفحه وجود ندارد)"}},{"pk":226,"model":"accounts.City","fields":{"name":"خواجه (شهر)"}},{"pk":227,"model":"accounts.City","fields":{"name":"خرمشهر"}},{"pk":228,"model":"accounts.City","fields":{"name":"خوانسار"}},{"pk":229,"model":"accounts.City","fields":{"name":"خوی"}},{"pk":230,"model":"accounts.City","fields":{"name":"داراب"}},{"pk":231,"model":"accounts.City","fields":{"name":"دزفول"}},{"pk":232,"model":"accounts.City","fields":{"name":"دوزدوزان"}},{"pk":233,"model":"accounts.City","fields":{"name":"داران"}},{"pk":234,"model":"accounts.City","fields":{"name":"دستجرد (شهر)"}},{"pk":235,"model":"accounts.City","fields":{"name":"دولت‌آباد (شهر) (صفحه وجود ندارد)"}},{"pk":236,"model":"accounts.City","fields":{"name":"داریان"}},{"pk":237,"model":"accounts.City","fields":{"name":"دستگرد"}},{"pk":238,"model":"accounts.City","fields":{"name":"دهگلان"}},{"pk":239,"model":"accounts.City","fields":{"name":"دامغان"}},{"pk":240,"model":"accounts.City","fields":{"name":"دلبران (شهر) (صفحه وجود ندارد)"}},{"pk":241,"model":"accounts.City","fields":{"name":"دهلران"}},{"pk":242,"model":"accounts.City","fields":{"name":"دانسفهان"}},{"pk":243,"model":"accounts.City","fields":{"name":"دلوار"}},{"pk":244,"model":"accounts.City","fields":{"name":"دیباج"}},{"pk":245,"model":"accounts.City","fields":{"name":"درچه‌پیاز"}},{"pk":246,"model":"accounts.City","fields":{"name":"دلیجان"}},{"pk":247,"model":"accounts.City","fields":{"name":"دیواندره"}},{"pk":248,"model":"accounts.City","fields":{"name":"درگز"}},{"pk":249,"model":"accounts.City","fields":{"name":"دماوند (شهر)"}},{"pk":250,"model":"accounts.City","fields":{"name":"دبیران"}},{"pk":251,"model":"accounts.City","fields":{"name":"دررود"}},{"pk":252,"model":"accounts.City","fields":{"name":"دورود"}},{"pk":253,"model":"accounts.City","fields":{"name":"درگهان"}},{"pk":254,"model":"accounts.City","fields":{"name":"دزج (شهر) (صفحه وجود ندارد)"}},{"pk":255,"model":"accounts.City","fields":{"name":"دوزه"}},{"pk":256,"model":"accounts.City","fields":{"name":"دره شهر"}},{"pk":257,"model":"accounts.City","fields":{"name":"دهاقا (صفحه وجود ندارد)"}},{"pk":258,"model":"accounts.City","fields":{"name":"دوگنبدان"}},{"pk":259,"model":"accounts.City","fields":{"name":"دهدشت"}},{"pk":260,"model":"accounts.City","fields":{"name":"رازمیان"}},{"pk":261,"model":"accounts.City","fields":{"name":"رزوه"}},{"pk":262,"model":"accounts.City","fields":{"name":"رودبار"}},{"pk":263,"model":"accounts.City","fields":{"name":"رامسر"}},{"pk":264,"model":"accounts.City","fields":{"name":"رستم‌آباد"}},{"pk":265,"model":"accounts.City","fields":{"name":"رودسر"}},{"pk":266,"model":"accounts.City","fields":{"name":"رامهرمز"}},{"pk":267,"model":"accounts.City","fields":{"name":"رشت"}},{"pk":268,"model":"accounts.City","fields":{"name":"رودهن"}},{"pk":269,"model":"accounts.City","fields":{"name":"رامیان"}},{"pk":270,"model":"accounts.City","fields":{"name":"رشتخوار"}},{"pk":271,"model":"accounts.City","fields":{"name":"رونیز"}},{"pk":272,"model":"accounts.City","fields":{"name":"راور"}},{"pk":273,"model":"accounts.City","fields":{"name":"رضوانشهر (اصفهان) (صفحه وجود ندارد)"}},{"pk":274,"model":"accounts.City","fields":{"name":"رویان"}},{"pk":275,"model":"accounts.City","fields":{"name":"رباط کریم"}},{"pk":276,"model":"accounts.City","fields":{"name":"رضوانشهر (گیلان)"}},{"pk":277,"model":"accounts.City","fields":{"name":"رویدر"}},{"pk":278,"model":"accounts.City","fields":{"name":"رزن"}},{"pk":279,"model":"accounts.City","fields":{"name":"رفسنجان"}},{"pk":280,"model":"accounts.City","fields":{"name":"ریگان"}},{"pk":281,"model":"accounts.City","fields":{"name":"رستم کلا"}},{"pk":282,"model":"accounts.City","fields":{"name":"رفیع"}},{"pk":283,"model":"accounts.City","fields":{"name":"رینه"}},{"pk":284,"model":"accounts.City","fields":{"name":"رزجرد"}},{"pk":285,"model":"accounts.City","fields":{"name":"زابل"}},{"pk":286,"model":"accounts.City","fields":{"name":"زرنق"}},{"pk":287,"model":"accounts.City","fields":{"name":"زواره"}},{"pk":288,"model":"accounts.City","fields":{"name":"زاهدان"}},{"pk":289,"model":"accounts.City","fields":{"name":"زرین‌شهر"}},{"pk":290,"model":"accounts.City","fields":{"name":"زهان"}},{"pk":291,"model":"accounts.City","fields":{"name":"زاهدشهر"}},{"pk":292,"model":"accounts.City","fields":{"name":"زرینه"}},{"pk":293,"model":"accounts.City","fields":{"name":"زیاران"}},{"pk":294,"model":"accounts.City","fields":{"name":"زرقان"}},{"pk":295,"model":"accounts.City","fields":{"name":"زنجان"}},{"pk":296,"model":"accounts.City","fields":{"name":"زازران"}},{"pk":297,"model":"accounts.City","fields":{"name":"زرند"}},{"pk":298,"model":"accounts.City","fields":{"name":"زنوز"}},{"pk":299,"model":"accounts.City","fields":{"name":"ساری"}},{"pk":300,"model":"accounts.City","fields":{"name":"سرعین"}},{"pk":301,"model":"accounts.City","fields":{"name":"سنندج"}},{"pk":302,"model":"accounts.City","fields":{"name":"ساوه"}},{"pk":303,"model":"accounts.City","fields":{"name":"سروآباد"}},{"pk":304,"model":"accounts.City","fields":{"name":"سوسنگرد"}},{"pk":305,"model":"accounts.City","fields":{"name":"سبزوار"}},{"pk":306,"model":"accounts.City","fields":{"name":"سروستان"}},{"pk":307,"model":"accounts.City","fields":{"name":"سوق (شهر)"}},{"pk":308,"model":"accounts.City","fields":{"name":"سپیدان"}},{"pk":309,"model":"accounts.City","fields":{"name":"سریش‌آباد"}},{"pk":310,"model":"accounts.City","fields":{"name":"سورشجان"}},{"pk":311,"model":"accounts.City","fields":{"name":"سده (شهر)"}},{"pk":312,"model":"accounts.City","fields":{"name":"سعادت‌شهر"}},{"pk":313,"model":"accounts.City","fields":{"name":"سه‌قلعه"}},{"pk":314,"model":"accounts.City","fields":{"name":"سراب (شهر)"}},{"pk":315,"model":"accounts.City","fields":{"name":"سفیددشت چهارمحال (صفحه وجود ندارد)"}},{"pk":316,"model":"accounts.City","fields":{"name":"سهند (شهر)"}},{"pk":317,"model":"accounts.City","fields":{"name":"سراوان"}},{"pk":318,"model":"accounts.City","fields":{"name":"سقز"}},{"pk":319,"model":"accounts.City","fields":{"name":"سنگر"}},{"pk":320,"model":"accounts.City","fields":{"name":"سرایان"}},{"pk":321,"model":"accounts.City","fields":{"name":"سگزی"}},{"pk":322,"model":"accounts.City","fields":{"name":"سلطانیه"}},{"pk":323,"model":"accounts.City","fields":{"name":"سربندر"}},{"pk":324,"model":"accounts.City","fields":{"name":"سلماس"}},{"pk":325,"model":"accounts.City","fields":{"name":"سیدان"}},{"pk":326,"model":"accounts.City","fields":{"name":"سربیشه"}},{"pk":327,"model":"accounts.City","fields":{"name":"سلمانشهر"}},{"pk":328,"model":"accounts.City","fields":{"name":"سیراف"}},{"pk":329,"model":"accounts.City","fields":{"name":"سرپل ذهاب"}},{"pk":330,"model":"accounts.City","fields":{"name":"سمنان"}},{"pk":331,"model":"accounts.City","fields":{"name":"سیرجان"}},{"pk":332,"model":"accounts.City","fields":{"name":"سرخس"}},{"pk":333,"model":"accounts.City","fields":{"name":"سمیرم"}},{"pk":334,"model":"accounts.City","fields":{"name":"سیس"}},{"pk":335,"model":"accounts.City","fields":{"name":"سرخه"}},{"pk":336,"model":"accounts.City","fields":{"name":"سنقر"}},{"pk":337,"model":"accounts.City","fields":{"name":"سیوند"}},{"pk":338,"model":"accounts.City","fields":{"name":"سردرود"}},{"pk":339,"model":"accounts.City","fields":{"name":"سنگسر"}},{"pk":340,"model":"accounts.City","fields":{"name":"سیاهکل"}},{"pk":341,"model":"accounts.City","fields":{"name":"سلطان شهر"}},{"pk":342,"model":"accounts.City","fields":{"name":"سیاه منصور"}},{"pk":343,"model":"accounts.City","fields":{"name":"شادگان"}},{"pk":344,"model":"accounts.City","fields":{"name":"شرفخانه"}},{"pk":345,"model":"accounts.City","fields":{"name":"شهربابک"}},{"pk":346,"model":"accounts.City","fields":{"name":"شازند"}},{"pk":347,"model":"accounts.City","fields":{"name":"شریف‌آباد (شهر) (صفحه وجود ندارد)"}},{"pk":348,"model":"accounts.City","fields":{"name":"شهر پیر"}},{"pk":349,"model":"accounts.City","fields":{"name":"شال (شهر)"}},{"pk":350,"model":"accounts.City","fields":{"name":"ششده"}},{"pk":351,"model":"accounts.City","fields":{"name":"شهرضا"}},{"pk":352,"model":"accounts.City","fields":{"name":"شاندیز"}},{"pk":353,"model":"accounts.City","fields":{"name":"شندآباد"}},{"pk":354,"model":"accounts.City","fields":{"name":"شهرکرد"}},{"pk":355,"model":"accounts.City","fields":{"name":"شاهدشهر"}},{"pk":356,"model":"accounts.City","fields":{"name":"شوش"}},{"pk":357,"model":"accounts.City","fields":{"name":"شهریار (شهر)"}},{"pk":358,"model":"accounts.City","fields":{"name":"شاهدیه"}},{"pk":359,"model":"accounts.City","fields":{"name":"شوسف"}},{"pk":360,"model":"accounts.City","fields":{"name":"شهمیرزاد"}},{"pk":361,"model":"accounts.City","fields":{"name":"شاهرود"}},{"pk":362,"model":"accounts.City","fields":{"name":"شوشتر"}},{"pk":363,"model":"accounts.City","fields":{"name":"شیروان"}},{"pk":364,"model":"accounts.City","fields":{"name":"شاهین‌شهر"}},{"pk":365,"model":"accounts.City","fields":{"name":"شویشه"}},{"pk":366,"model":"accounts.City","fields":{"name":"شهربیر (صفحه وجود ندارد)"}},{"pk":367,"model":"accounts.City","fields":{"name":"شبستر"}},{"pk":368,"model":"accounts.City","fields":{"name":"شهداد"}},{"pk":369,"model":"accounts.City","fields":{"name":"شیراز"}},{"pk":370,"model":"accounts.City","fields":{"name":"شربیان"}},{"pk":371,"model":"accounts.City","fields":{"name":"صاحب (شهر)"}},{"pk":372,"model":"accounts.City","fields":{"name":"صحنه"}},{"pk":373,"model":"accounts.City","fields":{"name":"صفاشهر"}},{"pk":374,"model":"accounts.City","fields":{"name":"صباشهر"}},{"pk":375,"model":"accounts.City","fields":{"name":"صغاد"}},{"pk":376,"model":"accounts.City","fields":{"name":"صوفیان"}},{"pk":377,"model":"accounts.City","fields":{"name":"صفادشت"}},{"pk":378,"model":"accounts.City","fields":{"name":"صومعه سرا"}},{"pk":379,"model":"accounts.City","fields":{"name":"ضیاءآباد"}},{"pk":380,"model":"accounts.City","fields":{"name":"ضیابر"}},{"pk":381,"model":"accounts.City","fields":{"name":"طالقان"}},{"pk":382,"model":"accounts.City","fields":{"name":"شهرک"}},{"pk":383,"model":"accounts.City","fields":{"name":"طبس مسینا"}},{"pk":384,"model":"accounts.City","fields":{"name":"طالخونچه"}},{"pk":385,"model":"accounts.City","fields":{"name":"طبس"}},{"pk":386,"model":"accounts.City","fields":{"name":"طرقبه"}},{"pk":387,"model":"accounts.City","fields":{"name":"عباس‌آباد"}},{"pk":388,"model":"accounts.City","fields":{"name":"عسگران"}},{"pk":389,"model":"accounts.City","fields":{"name":"علی‌آباد"}},{"pk":390,"model":"accounts.City","fields":{"name":"عجب شیر"}},{"pk":391,"model":"accounts.City","fields":{"name":"علامرودشت"}},{"pk":392,"model":"accounts.City","fields":{"name":"عنبران"}},{"pk":393,"model":"accounts.City","fields":{"name":"فارسان"}},{"pk":394,"model":"accounts.City","fields":{"name":"فریدون‌کنار"}},{"pk":395,"model":"accounts.City","fields":{"name":"فیرورق"}},{"pk":396,"model":"accounts.City","fields":{"name":"فاروق"}},{"pk":397,"model":"accounts.City","fields":{"name":"فریمان"}},{"pk":398,"model":"accounts.City","fields":{"name":"فیروزکوه"}},{"pk":399,"model":"accounts.City","fields":{"name":"فراشبند"}},{"pk":400,"model":"accounts.City","fields":{"name":"فسا"}},{"pk":401,"model":"accounts.City","fields":{"name":"فیروزآباد"}},{"pk":402,"model":"accounts.City","fields":{"name":"فردوس"}},{"pk":403,"model":"accounts.City","fields":{"name":"فشک"}},{"pk":404,"model":"accounts.City","fields":{"name":"فرخ شهر"}},{"pk":405,"model":"accounts.City","fields":{"name":"فردوسیه"}},{"pk":406,"model":"accounts.City","fields":{"name":"فشم"}},{"pk":407,"model":"accounts.City","fields":{"name":"فیض‌آباد (خراسان رضوی)"}},{"pk":408,"model":"accounts.City","fields":{"name":"فرهادگرد"}},{"pk":409,"model":"accounts.City","fields":{"name":"فلاورجان"}},{"pk":410,"model":"accounts.City","fields":{"name":"فیروزه"}},{"pk":411,"model":"accounts.City","fields":{"name":"فریدن"}},{"pk":412,"model":"accounts.City","fields":{"name":"فومن"}},{"pk":413,"model":"accounts.City","fields":{"name":"فریدونشهر"}},{"pk":414,"model":"accounts.City","fields":{"name":"قائم‌شهر"}},{"pk":415,"model":"accounts.City","fields":{"name":"قزوین"}},{"pk":416,"model":"accounts.City","fields":{"name":"قنوات"}},{"pk":417,"model":"accounts.City","fields":{"name":"قائمیه"}},{"pk":418,"model":"accounts.City","fields":{"name":"قشم"}},{"pk":419,"model":"accounts.City","fields":{"name":"قوچان"}},{"pk":420,"model":"accounts.City","fields":{"name":"قاین"}},{"pk":421,"model":"accounts.City","fields":{"name":"قصرشیرین"}},{"pk":422,"model":"accounts.City","fields":{"name":"قهستان (شهرستان درمیان)"}},{"pk":423,"model":"accounts.City","fields":{"name":"قادرآباد (شهر) (صفحه وجود ندارد)"}},{"pk":424,"model":"accounts.City","fields":{"name":"قطب‌آباد"}},{"pk":425,"model":"accounts.City","fields":{"name":"قیدار"}},{"pk":426,"model":"accounts.City","fields":{"name":"قدس (استان تهران) (صفحه وجود ندارد)"}},{"pk":427,"model":"accounts.City","fields":{"name":"قلعه‌تل"}},{"pk":428,"model":"accounts.City","fields":{"name":"قیروکارزین"}},{"pk":429,"model":"accounts.City","fields":{"name":"قرچک"}},{"pk":430,"model":"accounts.City","fields":{"name":"قم"}},{"pk":431,"model":"accounts.City","fields":{"name":"قاضی سملقان (صفحه وجود ندارد)"}},{"pk":432,"model":"accounts.City","fields":{"name":"قروه"}},{"pk":433,"model":"accounts.City","fields":{"name":"قمصر"}},{"pk":434,"model":"accounts.City","fields":{"name":"کازرون"}},{"pk":435,"model":"accounts.City","fields":{"name":"کلات (شهر) (صفحه وجود ندارد)"}},{"pk":436,"model":"accounts.City","fields":{"name":"کوار"}},{"pk":437,"model":"accounts.City","fields":{"name":"کاشان"}},{"pk":438,"model":"accounts.City","fields":{"name":"کلاته خیج"}},{"pk":439,"model":"accounts.City","fields":{"name":"کوچصفهان"}},{"pk":440,"model":"accounts.City","fields":{"name":"کاشمر"}},{"pk":441,"model":"accounts.City","fields":{"name":"کلاچای"}},{"pk":442,"model":"accounts.City","fields":{"name":"کوزه‌کنان"}},{"pk":443,"model":"accounts.City","fields":{"name":"کامفیروز"}},{"pk":444,"model":"accounts.City","fields":{"name":"کلارآباد"}},{"pk":445,"model":"accounts.City","fields":{"name":"کوشک (شهر)"}},{"pk":446,"model":"accounts.City","fields":{"name":"کامیاران"}},{"pk":447,"model":"accounts.City","fields":{"name":"کلاردشت"}},{"pk":448,"model":"accounts.City","fields":{"name":"کوهپایه (شهر)"}},{"pk":449,"model":"accounts.City","fields":{"name":"کانی‌سور"}},{"pk":450,"model":"accounts.City","fields":{"name":"کلاله"}},{"pk":451,"model":"accounts.City","fields":{"name":"کوهدشت"}},{"pk":452,"model":"accounts.City","fields":{"name":"کبوترآهنگ"}},{"pk":453,"model":"accounts.City","fields":{"name":"کبودرآهنگ"}},{"pk":454,"model":"accounts.City","fields":{"name":"کبود رآهنگ"}},{"pk":455,"model":"accounts.City","fields":{"name":"کلوانق"}},{"pk":456,"model":"accounts.City","fields":{"name":"کوهین"}},{"pk":457,"model":"accounts.City","fields":{"name":"کرج"}},{"pk":458,"model":"accounts.City","fields":{"name":"کلور"}},{"pk":459,"model":"accounts.City","fields":{"name":"کهریزک"}},{"pk":460,"model":"accounts.City","fields":{"name":"کردکوی"}},{"pk":461,"model":"accounts.City","fields":{"name":"کلیبر"}},{"pk":462,"model":"accounts.City","fields":{"name":"کهک"}},{"pk":463,"model":"accounts.City","fields":{"name":"کرمان"}},{"pk":464,"model":"accounts.City","fields":{"name":"کمال‌شهر"}},{"pk":465,"model":"accounts.City","fields":{"name":"کهنوج"}},{"pk":466,"model":"accounts.City","fields":{"name":"کرمانشاه"}},{"pk":467,"model":"accounts.City","fields":{"name":"کمشجه"}},{"pk":468,"model":"accounts.City","fields":{"name":"کیش"}},{"pk":469,"model":"accounts.City","fields":{"name":"کرند غرب"}},{"pk":470,"model":"accounts.City","fields":{"name":"کمه"}},{"pk":471,"model":"accounts.City","fields":{"name":"کیلان"}},{"pk":472,"model":"accounts.City","fields":{"name":"کره‌ای (شهر)"}},{"pk":473,"model":"accounts.City","fields":{"name":"کنارتخته"}},{"pk":474,"model":"accounts.City","fields":{"name":"کوهنجان"}},{"pk":475,"model":"accounts.City","fields":{"name":"کشک‌سرای"}},{"pk":476,"model":"accounts.City","fields":{"name":"کنگاور"}},{"pk":477,"model":"accounts.City","fields":{"name":"کیاشهر"}},{"pk":478,"model":"accounts.City","fields":{"name":"کاخک"}},{"pk":479,"model":"accounts.City","fields":{"name":"گالیکش"}},{"pk":480,"model":"accounts.City","fields":{"name":"گز (شهر)"}},{"pk":481,"model":"accounts.City","fields":{"name":"گمیشان"}},{"pk":482,"model":"accounts.City","fields":{"name":"گچساران"}},{"pk":483,"model":"accounts.City","fields":{"name":"گلباف"}},{"pk":484,"model":"accounts.City","fields":{"name":"گناباد"}},{"pk":485,"model":"accounts.City","fields":{"name":"گراش"}},{"pk":486,"model":"accounts.City","fields":{"name":"گلپایگان"}},{"pk":487,"model":"accounts.City","fields":{"name":"گناوه"}},{"pk":488,"model":"accounts.City","fields":{"name":"گرگان"}},{"pk":489,"model":"accounts.City","fields":{"name":"گلستان (شهر) (صفحه وجود ندارد)"}},{"pk":490,"model":"accounts.City","fields":{"name":"گنبد کاووس"}},{"pk":491,"model":"accounts.City","fields":{"name":"گرمسار"}},{"pk":492,"model":"accounts.City","fields":{"name":"گلوگاه"}},{"pk":493,"model":"accounts.City","fields":{"name":"گیلان غرب"}},{"pk":494,"model":"accounts.City","fields":{"name":"گرمی"}},{"pk":495,"model":"accounts.City","fields":{"name":"گله‌دار"}},{"pk":496,"model":"accounts.City","fields":{"name":"گهواره (شهر)"}},{"pk":497,"model":"accounts.City","fields":{"name":"گوگد"}},{"pk":498,"model":"accounts.City","fields":{"name":"لامرد"}},{"pk":499,"model":"accounts.City","fields":{"name":"لپوئی"}},{"pk":500,"model":"accounts.City","fields":{"name":"لواسان"}},{"pk":501,"model":"accounts.City","fields":{"name":"لار"}},{"pk":502,"model":"accounts.City","fields":{"name":"لردگان"}},{"pk":503,"model":"accounts.City","fields":{"name":"لوشان"}},{"pk":504,"model":"accounts.City","fields":{"name":"لاهیجان"}},{"pk":505,"model":"accounts.City","fields":{"name":"لنگرود"}},{"pk":506,"model":"accounts.City","fields":{"name":"لاهرود"}},{"pk":507,"model":"accounts.City","fields":{"name":"ماسال"}},{"pk":508,"model":"accounts.City","fields":{"name":"مرودشت"}},{"pk":509,"model":"accounts.City","fields":{"name":"مهاباد"}},{"pk":510,"model":"accounts.City","fields":{"name":"ماسوله"}},{"pk":511,"model":"accounts.City","fields":{"name":"مریوان"}},{"pk":512,"model":"accounts.City","fields":{"name":"مهاباد (اصفهان)"}},{"pk":513,"model":"accounts.City","fields":{"name":"ماکو"}},{"pk":514,"model":"accounts.City","fields":{"name":"مسجدسلیمان"}},{"pk":515,"model":"accounts.City","fields":{"name":"مهدی‌شهر"}},{"pk":516,"model":"accounts.City","fields":{"name":"ماهان"}},{"pk":517,"model":"accounts.City","fields":{"name":"مشکان (صفحه وجود ندارد)"}},{"pk":518,"model":"accounts.City","fields":{"name":"مهر (شهر)"}},{"pk":519,"model":"accounts.City","fields":{"name":"ماه‌دشت (صفحه وجود ندارد)"}},{"pk":520,"model":"accounts.City","fields":{"name":"مشکین‌دشت"}},{"pk":521,"model":"accounts.City","fields":{"name":"مهران"}},{"pk":522,"model":"accounts.City","fields":{"name":"ماه‌شهر"}},{"pk":523,"model":"accounts.City","fields":{"name":"مشکین‌شهر"}},{"pk":524,"model":"accounts.City","fields":{"name":"مهریز"}},{"pk":525,"model":"accounts.City","fields":{"name":"مبارکه"}},{"pk":526,"model":"accounts.City","fields":{"name":"مشهد"}},{"pk":527,"model":"accounts.City","fields":{"name":"میامی (ایران) (صفحه وجود ندارد)"}},{"pk":528,"model":"accounts.City","fields":{"name":"مجن"}},{"pk":529,"model":"accounts.City","fields":{"name":"مصیری"}},{"pk":530,"model":"accounts.City","fields":{"name":"میاندشت"}},{"pk":531,"model":"accounts.City","fields":{"name":"محلات"}},{"pk":532,"model":"accounts.City","fields":{"name":"معلم‌کلایه"}},{"pk":533,"model":"accounts.City","fields":{"name":"میاندوآب"}},{"pk":534,"model":"accounts.City","fields":{"name":"محمدآباد (شهر)"}},{"pk":535,"model":"accounts.City","fields":{"name":"ملارد"}},{"pk":536,"model":"accounts.City","fields":{"name":"میانه"}},{"pk":537,"model":"accounts.City","fields":{"name":"محمدآباد (شهر در اصفهان)"}},{"pk":538,"model":"accounts.City","fields":{"name":"ملایر"}},{"pk":539,"model":"accounts.City","fields":{"name":"میبد"}},{"pk":540,"model":"accounts.City","fields":{"name":"محمدشهر"}},{"pk":541,"model":"accounts.City","fields":{"name":"ملکان (ملک کندی) (صفحه وجود ندارد)"}},{"pk":542,"model":"accounts.City","fields":{"name":"میرجاوه"}},{"pk":543,"model":"accounts.City","fields":{"name":"محمودآباد"}},{"pk":544,"model":"accounts.City","fields":{"name":"منجیل"}},{"pk":545,"model":"accounts.City","fields":{"name":"میمند"}},{"pk":546,"model":"accounts.City","fields":{"name":"محمودآباد نمونه"}},{"pk":547,"model":"accounts.City","fields":{"name":"منظریه (شهر) (صفحه وجود ندارد)"}},{"pk":548,"model":"accounts.City","fields":{"name":"میمه"}},{"pk":549,"model":"accounts.City","fields":{"name":"مراغه"}},{"pk":550,"model":"accounts.City","fields":{"name":"موچش"}},{"pk":551,"model":"accounts.City","fields":{"name":"میناب"}},{"pk":552,"model":"accounts.City","fields":{"name":"مرزن آباد"}},{"pk":553,"model":"accounts.City","fields":{"name":"مود"}},{"pk":554,"model":"accounts.City","fields":{"name":"مینودشت"}},{"pk":555,"model":"accounts.City","fields":{"name":"مرند"}},{"pk":556,"model":"accounts.City","fields":{"name":"مورچه خورت"}},{"pk":557,"model":"accounts.City","fields":{"name":"مه شهر (آبی بیگلو) (صفحه وجود ندارد)"}},{"pk":558,"model":"accounts.City","fields":{"name":"ماکلوان"}},{"pk":559,"model":"accounts.City","fields":{"name":"مارلیک"}},{"pk":560,"model":"accounts.City","fields":{"name":"نایین"}},{"pk":561,"model":"accounts.City","fields":{"name":"نقده"}},{"pk":562,"model":"accounts.City","fields":{"name":"نهاوند"}},{"pk":563,"model":"accounts.City","fields":{"name":"نجف آباد"}},{"pk":564,"model":"accounts.City","fields":{"name":"نکا"}},{"pk":565,"model":"accounts.City","fields":{"name":"نهبندان"}},{"pk":566,"model":"accounts.City","fields":{"name":"نراق"}},{"pk":567,"model":"accounts.City","fields":{"name":"نمین"}},{"pk":568,"model":"accounts.City","fields":{"name":"نیریز"}},{"pk":569,"model":"accounts.City","fields":{"name":"نسیم‌شهر"}},{"pk":570,"model":"accounts.City","fields":{"name":"نودان"}},{"pk":571,"model":"accounts.City","fields":{"name":"نوش آباد"}},{"pk":572,"model":"accounts.City","fields":{"name":"نشتارود"}},{"pk":573,"model":"accounts.City","fields":{"name":"نور"}},{"pk":574,"model":"accounts.City","fields":{"name":"نیشابور"}},{"pk":575,"model":"accounts.City","fields":{"name":"نصرآباد"}},{"pk":576,"model":"accounts.City","fields":{"name":"نورآباد"}},{"pk":577,"model":"accounts.City","fields":{"name":"نیک‌آباد"}},{"pk":578,"model":"accounts.City","fields":{"name":"نطنز"}},{"pk":579,"model":"accounts.City","fields":{"name":"نوشهر"}},{"pk":580,"model":"accounts.City","fields":{"name":"نیمبلوک"}},{"pk":581,"model":"accounts.City","fields":{"name":"نظرآباد"}},{"pk":582,"model":"accounts.City","fields":{"name":"نوکنده"}},{"pk":583,"model":"accounts.City","fields":{"name":"ناغان"}},{"pk":584,"model":"accounts.City","fields":{"name":"واجارگاه"}},{"pk":585,"model":"accounts.City","fields":{"name":"وحیدیه"}},{"pk":586,"model":"accounts.City","fields":{"name":"ورزنه"}},{"pk":587,"model":"accounts.City","fields":{"name":"وایقان"}},{"pk":588,"model":"accounts.City","fields":{"name":"ورامین"}},{"pk":589,"model":"accounts.City","fields":{"name":"وزوان"}},{"pk":590,"model":"accounts.City","fields":{"name":"وحدتیه"}},{"pk":591,"model":"accounts.City","fields":{"name":"وراوی"}},{"pk":592,"model":"accounts.City","fields":{"name":"ونک (اصفهان)"}},{"pk":593,"model":"accounts.City","fields":{"name":"ویس (شهر)"}},{"pk":594,"model":"accounts.City","fields":{"name":"هادی‌شهر"}},{"pk":595,"model":"accounts.City","fields":{"name":"هشترود"}},{"pk":596,"model":"accounts.City","fields":{"name":"هندیجان"}},{"pk":597,"model":"accounts.City","fields":{"name":"هرسین"}},{"pk":598,"model":"accounts.City","fields":{"name":"هشتگرد"}},{"pk":599,"model":"accounts.City","fields":{"name":"هویزه"}},{"pk":600,"model":"accounts.City","fields":{"name":"هرند"}},{"pk":601,"model":"accounts.City","fields":{"name":"هفت تپه"}},{"pk":602,"model":"accounts.City","fields":{"name":"هیدج"}},{"pk":603,"model":"accounts.City","fields":{"name":"هشتپر"}},{"pk":604,"model":"accounts.City","fields":{"name":"همدان"}},{"pk":605,"model":"accounts.City","fields":{"name":"هرات (یزد)"}},{"pk":606,"model":"accounts.City","fields":{"name":"هماشهر"}},{"pk":607,"model":"accounts.City","fields":{"name":"یاسوج"}},{"pk":608,"model":"accounts.City","fields":{"name":"یاسوکند"}},{"pk":609,"model":"accounts.City","fields":{"name":"یزد"}},{"pk":1,"model":"jobs.Skill","fields":{"name":"جاوا"}},{"pk":2,"model":"jobs.Skill","fields":{"name":"پایتون"}},{"pk":3,"model":"jobs.Skill","fields":{"name":"استارت کامپیوتر"}},{"pk":4,"model":"jobs.Skill","fields":{"name":"مدیریت شبکه"}},{"pk":5,"model":"jobs.Skill","fields":{"name":"اسکالا"}},{"pk":6,"model":"jobs.Skill","fields":{"name":"لینوکس"}},{"pk":7,"model":"jobs.Skill","fields":{"name":"ویندوز"}},{"pk":8,"model":"jobs.Skill","fields":{"name":"یونیکس"}},{"pk":9,"model":"jobs.Skill","fields":{"name":"برنامه‌نویسی اندروید"}},{"pk":10,"model":"jobs.Skill","fields":{"name":"کار با اندروید"}},{"pk":11,"model":"jobs.Skill","fields":{"name":"روبی"}},{"pk":12,"model":"jobs.Skill","fields":{"name":"پایگاه‌داده"}},{"pk":13,"model":"jobs.Skill","fields":{"name":"طراحی رابط‌ کاربری"}},{"pk":14,"model":"jobs.Skill","fields":{"name":"تحلیل سامانه"}},{"pk":15,"model":"jobs.Skill","fields":{"name":"گیت"}},{"pk":16,"model":"jobs.Skill","fields":{"name":"اسکریپت نویسی"}},{"pk":17,"model":"jobs.Skill","fields":{"name":"طراحی الگوریتم"}},{"pk":18,"model":"jobs.Skill","fields":{"name":"بهینه‌سازی"}},{"pk":19,"model":"jobs.Skill","fields":{"name":"هک و نفوذ"}},{"pk":20,"model":"jobs.Skill","fields":{"name":"جنگو"}},{"pk":21,"model":"jobs.Skill","fields":{"name":"پی‌اچ‌پی"}},{"pk":22,"model":"jobs.Skill","fields":{"name":"برنامه‌نویسی شبکه"}},{"pk":23,"model":"jobs.Skill","fields":{"name":"برنامه‌نویسی وب"}},{"pk":24,"model":"jobs.Skill","fields":{"name":"مدیریت پروژه"}},{"pk":25,"model":"jobs.Skill","fields":{"name":"نصب لینوکس"}},{"pk":26,"model":"jobs.Skill","fields":{"name":"کرنل نویسی لینوکس"}},{"pk":27,"model":"jobs.Skill","fields":{"name":"نصب ویندوز"}},{"pk":28,"model":"jobs.Skill","fields":{"name":"مدیریت لینوکس"}},{"pk":29,"model":"jobs.Skill","fields":{"name":"پایگاه‌داده اس‌کیو‌ال"}}]